annotationengine/__init__.py
annotationengine/anno_database.py
annotationengine/annotation.py
annotationengine/config.py
annotationengine/dataset.py
annotationengine/errors.py
annotationengine/utils.py
annotationengine-1.0.5.dist-info/DESCRIPTION.rst
annotationengine-1.0.5.dist-info/METADATA
annotationengine-1.0.5.dist-info/RECORD
annotationengine-1.0.5.dist-info/WHEEL
annotationengine-1.0.5.dist-info/metadata.json
annotationengine-1.0.5.dist-info/top_level.txt
