Metadata-Version: 2.0
Name: annotationengine
Version: 1.0.5
Summary: a service for storing arbitrary annotation data on EM volumes stored in a cloud volume 
Home-page: https://github.com/fcollman/AnnotationEngine
Author: Forrest Collman
Author-email: forrestc@alleninstitute.org
License: UNKNOWN
Platform: UNKNOWN
Requires-Dist: numpy
Requires-Dist: Flask
Requires-Dist: pandas
Requires-Dist: dynamicannotationdb (>=1.0.0)
Requires-Dist: emannotationschemas (>=0.2.15)
Requires-Dist: multiwrapper
Requires-Dist: jsonschema
